README
setup.cfg
setup.py
Flask_Navigate.egg-info/PKG-INFO
Flask_Navigate.egg-info/SOURCES.txt
Flask_Navigate.egg-info/dependency_links.txt
Flask_Navigate.egg-info/top_level.txt
flask_navigate/__init__.py
flask_navigate/_compat.py
flask_navigate/helper.py
flask_navigate/models.py
flask_navigate/templates.py
flask_navigate/views.py