Metadata-Version: 1.0
Name: Flask-Navigate
Version: 0.2.2
Summary: Another flask extension that provides Navigation menus.
Home-page: https://github.com/bschumacher/Flask-Navigate
Author: Bill Schumacher
Author-email: bill@servernet.co
License: LGPLv3
Keywords: flask nav navigation menu
Platform: UNKNOWN
